README.rst
setup.cfg
setup.py
psclient/__init__.py
psclient/_ec2_config.py
psclient/aws.py
psclient/cluster_client.py
psclient/config.py
psclient/connect_fn.py
psclient/constants.py
psclient/create_fn.py
psclient/custom_query_predictive_object.py
psclient/decorators.py
psclient/file_util.py
psclient/logparse.py
psclient/main.py
psclient/manager_client.py
psclient/model_predictive_object.py
psclient/policy.py
psclient/predictive_object.py
psclient/predictive_service_client.py
psclient/query_client.py
psclient/r_predictive_object.py
psclient/rest.py
psclient/schema.py
psclient/server_environment.py
psclient/state_util.py
psclient/upgrade_fn.py
psclient/util.py
psclient.egg-info/PKG-INFO
psclient.egg-info/SOURCES.txt
psclient.egg-info/dependency_links.txt
psclient.egg-info/entry_points.txt
psclient.egg-info/requires.txt
psclient.egg-info/top_level.txt