Metadata-Version: 1.1
Name: psclient
Version: 0.0.5
Summary: Predictive Services Management Client
Home-page: https://github.com/turi-code/psclient
Author: Turi, Inc.
Author-email: contact@turi.com
License: LICENSE
Keywords: turi graphlab predictive services
Platform: UNKNOWN
Classifier: Development Status :: 3 - Alpha
Classifier: Intended Audience :: Developers
Classifier: License :: OSI Approved :: BSD License
Classifier: Programming Language :: Python :: 2.7
Classifier: Topic :: Scientific/Engineering
Classifier: Topic :: Scientific/Engineering :: Information Analysis
